{
    "data": [
        {
            "name": "",
            "data": [
                {
                    "x": "大園測站",
                    "y": 60.8896
                },
                {
                    "x": "觀音測站",
                    "y": 65.3314
                },
                {
                    "x": "龍潭測站",
                    "y": 59.3946
                },
                {
                    "x": "平鎮測站",
                    "y": 56.4088
                },
                {
                    "x": "桃園測站",
                    "y": 57.6988
                },
                {
                    "x": "中壢測站",
                    "y": 38.1384
                }
            ]
        }
    ]
}